{"id": "noos001", "name": "Audio_Trans_08_698_06_04", "res": null, "contents": [[{"id": 0, "type": "bgm", "attrs": ["Station"], "content": ""}, {"id": 1, "type": "conversation", "attrs": ["Cleaner A"], "content": "Sir... Sir...?\n"}, {"id": 2, "type": "sound", "attrs": ["ROBO_On", "ROBO_Head  Start-Up"], "content": ""}, {"id": 3, "type": "conversation", "attrs": ["[ROBO_Head]"], "content": "<i>This unit, start-up, success. Running self-diagnostics... incomplete.\nDetect multiple physical damages on hardware.</i>\n"}, {"id": 4, "type": "conversation", "attrs": ["Cleaner B"], "content": "What the heck? A proxy robot?\nThis train has already ended service for the day. Please leave the carriage. We need to clean up.\n"}, {"id": 5, "type": "conversation", "attrs": ["[ROBO_Head]"], "content": "<i>......\nQuestion: This location... coordinates... ?</i>\n"}, {"id": 6, "type": "conversation", "attrs": ["Cleaner A"], "content": "Huh? This is Node 08. Where are you connected to? Can you hear us, owner of this robot? Please get this thing moving.\n"}, {"id": 7, "type": "conversation", "attrs": ["[ROBO_Head]"], "content": "<i>......\nWhere is Nora?</i>\n"}, {"id": 8, "type": "conversation", "attrs": ["Cleaner B"], "content": "Huh? What? Is it broken?\nWhat should we do? Contact the station staff?\n"}, {"id": 9, "type": "conversation", "attrs": ["Cleaner A"], "content": "Yeah. This is platform B. We've discovered a malfunctioning proxy robot. It seems to be disconnected from its owner. We are having trouble dealing with it. Please send someone over to help...\n"}, {"id": 10, "type": "conversation", "attrs": ["[ROBO_Head]"], "content": "<i>Apologies.</i>\n"}, {"id": 11, "type": "sound", "attrs": ["ROBO_Step", "Footsteps"], "content": ""}, {"id": 12, "type": "conversation", "attrs": ["Cleaner B"], "content": "Eh? HEY!\n"}, {"id": 13, "type": "text", "attrs": [], "content": "<i>[→Signal Switches]</i>\n"}, {"id": 14, "type": "conversation", "attrs": ["[ROBO_Head]"], "content": "<i>Inputting activity planning...\nOperation/Action denied; reasoning: conflict with supreme command.</i>\n"}, {"id": 15, "type": "conversation", "attrs": ["[ROBO_Head]"], "content": "<i>......</i>\n"}, {"id": 16, "type": "conversation", "attrs": ["[ROBO_Head]"], "content": "<i>Inputting activity planning...\nOperation/Action denied; reasoning: conflict with supreme command.</i>\n"}, {"id": 17, "type": "conversation", "attrs": ["[ROBO_Head]"], "content": "<i>......</i>\n"}, {"id": 18, "type": "conversation", "attrs": ["[ROBO_Head]"], "content": "<i>Loading Local.log...... 100%\nPrevious Shutdown: 698/06/02\n23:16:50'23\"\nDuring shutdown, one video message recorded:\nCam_Robo_698_06_02</i>\n"}, {"id": 19, "type": "conversation", "attrs": ["[ROBO_Head]"], "content": "<i>......</i>\n"}, {"id": 20, "type": "conversation", "attrs": ["[ROBO_Head]"], "content": "<i>Play video: Cam_Robo_697_04_06_01</i>\n"}, {"id": 21, "type": "conversation", "attrs": ["[ROBO_Head]"], "content": "<i>......</i>\n"}, {"id": 22, "type": "conversation", "attrs": ["[ROBO_Head]"], "content": "<i>Replay invalid.\nMemory unit reset error. Please select other files for troubleshooting.</i>\n"}, {"id": 23, "type": "conversation", "attrs": ["[ROBO_Head]"], "content": "<i>......</i>\n"}, {"id": 24, "type": "conversation", "attrs": ["[ROBO_Head]"], "content": "<i>Play video: Cam_Robo_697_04_06_01</i>\n"}, {"id": 25, "type": "conversation", "attrs": ["[ROBO_Head]"], "content": "<i>Begin replay.</i>\n"}, {"id": 26, "type": "text", "attrs": [], "content": "<i>[Signal Lost]</i>\n"}], [{"id": 0, "type": "bgm", "attrs": ["Station"], "content": ""}, {"id": 1, "type": "conversation", "attrs": ["清掃スタッフA"], "content": "すみません……あの……？\n"}, {"id": 2, "type": "sound", "attrs": ["ROBO_On", "ROBO_Head スタートアップ"], "content": ""}, {"id": 3, "type": "conversation", "attrs": ["[ROBO_Head]"], "content": "<i>本機は正常に起動されています。自己診断中……まだ終了していません。\nハードウェアに複数の物理的破損を確認しました。</i>\n"}, {"id": 4, "type": "conversation", "attrs": ["清掃スタッフB"], "content": "なんだこれ？代理ロボットか？\nもう終点ですよ。\n早く降りてください。\n掃除するんで。\n"}, {"id": 5, "type": "conversation", "attrs": ["[ROBO_Head]"], "content": "<i>………\nクエスチョン：ここの……座標を教えてください。</i>\n"}, {"id": 6, "type": "conversation", "attrs": ["清掃スタッフA"], "content": "あ？Node08ですけど？\nどこから接続してんすか？\n早くこのロボットどかしてくださいよ。\n"}, {"id": 7, "type": "conversation", "attrs": ["[ROBO_Head]"], "content": "<i>………\nNoraはどこですか？</i>\n"}, {"id": 8, "type": "conversation", "attrs": ["清掃スタッフB"], "content": "は？なんだ？ショートしてんのか？\nどうするかな……\n駅員に連絡するか……\n"}, {"id": 9, "type": "conversation", "attrs": ["清掃スタッフA"], "content": "はい、B番線ホームです。\n壊れた代理ロボットを発見しました。\n持ち主との接続も切れてるみたいです。\n邪魔なので、処理をお願いします。\n"}, {"id": 10, "type": "conversation", "attrs": ["[ROBO_Head]"], "content": "<i>失礼します。</i>\n"}, {"id": 11, "type": "sound", "attrs": ["ROBO_Step", "<i>足音</i>"], "content": ""}, {"id": 12, "type": "conversation", "attrs": ["清掃スタッフB"], "content": "おい！\n"}, {"id": 13, "type": "text", "attrs": [], "content": "<i>[→シグナル切り替え]</i>\n"}, {"id": 14, "type": "conversation", "attrs": ["[ROBO_Head]"], "content": "<i>行動プランを入力します……\n操作/行為が拒否されました。\n最高指令に反しています。</i>\n"}, {"id": 15, "type": "conversation", "attrs": ["[ROBO_Head]"], "content": "<i>………</i>\n"}, {"id": 16, "type": "conversation", "attrs": ["[ROBO_Head]"], "content": "<i>行動プランを入力します……\n操作/行為が拒否されました。\n最高指令に反しています。</i>\n"}, {"id": 17, "type": "conversation", "attrs": ["[ROBO_Head]"], "content": "<i>………</i>\n"}, {"id": 18, "type": "conversation", "attrs": ["[ROBO_Head]"], "content": "<i>Local.log読み込み中……100%\n前回のシャットダウン記録：698/06/02 23:16:50'23\"\nシャットダウン中に1件のビデオメッセージがあります：Cam_Robo_698_06_02</i>\n"}, {"id": 19, "type": "conversation", "attrs": ["[ROBO_Head]"], "content": "<i>………</i>\n"}, {"id": 20, "type": "conversation", "attrs": ["[ROBO_Head]"], "content": "<i>メッセージ再生：Cam_Robo_698_06_02</i>\n"}, {"id": 21, "type": "conversation", "attrs": ["[ROBO_Head]"], "content": "<i>………</i>\n"}, {"id": 22, "type": "conversation", "attrs": ["[ROBO_Head]"], "content": "<i>再生に失敗しました。\nメモリユニットリセットエラーです。\n他のデータを選択して、デバッグしてください。</i>\n"}, {"id": 23, "type": "conversation", "attrs": ["[ROBO_Head]"], "content": "<i>………</i>\n"}, {"id": 24, "type": "conversation", "attrs": ["[ROBO_Head]"], "content": "<i>メッセージを再生します：Cam_Robo_697_04_06_1</i>\n"}, {"id": 25, "type": "conversation", "attrs": ["[ROBO_Head]"], "content": "<i>再生します。</i>\n"}, {"id": 26, "type": "text", "attrs": [], "content": "<i>[電波切断]</i>\n"}], [{"id": 0, "type": "bgm", "attrs": ["Station"], "content": ""}, {"id": 1, "type": "conversation", "attrs": ["清潔工 A"], "content": "先生……先生……？\n"}, {"id": 2, "type": "sound", "attrs": ["ROBO_On", "ROBO_Head 啟動"], "content": ""}, {"id": 3, "type": "conversation", "attrs": ["[ROBO_Head]"], "content": "<i>本機，已正常啟動，執行自我診斷……未完成。\n偵測到硬體多處發生物理損傷。</i>\n"}, {"id": 4, "type": "conversation", "attrs": ["清潔工 B"], "content": "搞什麼啊？代理機器人嗎？\n這班列車已經停止服務囉，請快點下車，我們要打掃了。\n"}, {"id": 5, "type": "conversation", "attrs": ["[ROBO_Head]"], "content": "<i>……。\n提問：此處……座標位置？</i>\n"}, {"id": 6, "type": "conversation", "attrs": ["清潔工 A"], "content": "啊？Node 08 啊。你在哪裡連線操作的啊？請趕快把機器人開走。\n"}, {"id": 7, "type": "conversation", "attrs": ["[ROBO_Head]"], "content": "<i>……。\nNora 呢？</i>\n"}, {"id": 8, "type": "conversation", "attrs": ["清潔工 B"], "content": "吭？什麼啊？是秀逗了嗎？\n怎麼辦？要通知站務所嗎？\n"}, {"id": 9, "type": "conversation", "attrs": ["清潔工 A"], "content": "嗯。這裡是 B 月台，發現一台破損的代理機器人，好像已經跟主人斷線了，它在這邊造成我們困擾，請派人來處理……\n"}, {"id": 10, "type": "conversation", "attrs": ["[ROBO_Head]"], "content": "<i>失禮了。</i>\n"}, {"id": 11, "type": "sound", "attrs": ["ROBO_Step", "腳步"], "content": ""}, {"id": 12, "type": "conversation", "attrs": ["清潔工 B"], "content": "欸，喂！\n"}, {"id": 13, "type": "text", "attrs": [], "content": "<i>[→切換訊號]</i>\n"}, {"id": 14, "type": "conversation", "attrs": ["[ROBO_Head]"], "content": "<i>輸入行動規劃……\n操作/行為遭拒，與最高指令衝突。</i>\n"}, {"id": 15, "type": "conversation", "attrs": ["[ROBO_Head]"], "content": "<i>……。</i>\n"}, {"id": 16, "type": "conversation", "attrs": ["[ROBO_Head]"], "content": "<i>輸入行動規劃……\n操作/行為遭拒，與最高指令衝突。</i>\n"}, {"id": 17, "type": "conversation", "attrs": ["[ROBO_Head]"], "content": "<i>……。</i>\n"}, {"id": 18, "type": "conversation", "attrs": ["[ROBO_Head]"], "content": "<i>讀取 Local.log……100%\n上一次關機紀錄：698/06/02 23:16:50'23\"\n關機中有一則錄影訊息：Cam_Robo_698_06_02</i>\n"}, {"id": 19, "type": "conversation", "attrs": ["[ROBO_Head]"], "content": "<i>……。</i>\n"}, {"id": 20, "type": "conversation", "attrs": ["[ROBO_Head]"], "content": "<i>播放錄影：Cam_Robo_698_06_02</i>\n"}, {"id": 21, "type": "conversation", "attrs": ["[ROBO_Head]"], "content": "<i>……。</i>\n"}, {"id": 22, "type": "conversation", "attrs": ["[ROBO_Head]"], "content": "<i>播放失敗。\n記憶單元重置錯誤，請選擇其他檔案以供偵錯。</i>\n"}, {"id": 23, "type": "conversation", "attrs": ["[ROBO_Head]"], "content": "<i>……。</i>\n"}, {"id": 24, "type": "conversation", "attrs": ["[ROBO_Head]"], "content": "<i>播放錄影：Cam_Robo_697_04_06_1</i>\n"}, {"id": 25, "type": "conversation", "attrs": ["[ROBO_Head]"], "content": "<i>開始播放。</i>\n"}, {"id": 26, "type": "text", "attrs": [], "content": "<i>[訊號中斷]</i>\n"}], [{"id": 0, "type": "bgm", "attrs": ["Station"], "content": ""}, {"id": 1, "type": "conversation", "attrs": ["청소부 A"], "content": "선생님...? 선생님....?\n"}, {"id": 2, "type": "sound", "attrs": ["ROBO_On", "ROBO_Head 부팅"], "content": ""}, {"id": 3, "type": "conversation", "attrs": ["[ROBO_Head]"], "content": "<i>본 기기가 정상적으로 부팅되었습니다. 자아 진단을 시작합니다... 진행 중. 하드웨어 곳곳에 물리적 손상을 감지했습니다.</i>\n"}, {"id": 4, "type": "conversation", "attrs": ["청소부 B"], "content": "뭘 하는 거지? 대리 로봇인가?\n이 열차는 이미 운행이 끝났다고요~ 빨리 내리세요! 청소해야 하니깐.\n"}, {"id": 5, "type": "conversation", "attrs": ["[ROBO_Head]"], "content": "<i>......\n질문: 이곳...... 위치의 좌표는?</i>\n"}, {"id": 6, "type": "conversation", "attrs": ["청소부 A"], "content": "네? 여기는 Node 08입니다만. \n어디서 조종하고 있는 거지? 들리세요? 어쨌든 빨리 이 로봇 조종해서 밖으로 내보내주세요~!\n"}, {"id": 7, "type": "conversation", "attrs": ["[ROBO_Head]"], "content": "<i>……\nNora는?</i>\n"}, {"id": 8, "type": "conversation", "attrs": ["청소부 B"], "content": "앙!? 뭐야? 맛이 간 건가?\n어떡하지? 역무소에 알려야 하나...?\n"}, {"id": 9, "type": "conversation", "attrs": ["청소부 A"], "content": "그렇게 해야지.\n여기는 B 플랫폼. 망가진 대리 로봇 한 대를 발견했습니다. 주인하고도 이미 접속이 끊긴 것 같습니다만. 이거 때문에 조금 애를 먹고 있으니 거기 사람 좀 불러서 처리 부탁 드리....\n"}, {"id": 10, "type": "conversation", "attrs": ["[ROBO_Head]"], "content": "<i>실례했습니다.</i>\n"}, {"id": 11, "type": "sound", "attrs": ["ROBO_Step", "<i>발걸음</i>"], "content": ""}, {"id": 12, "type": "conversation", "attrs": ["청소부 B"], "content": "우왓! 여보세요!?\n"}, {"id": 13, "type": "text", "attrs": [], "content": "<i>[→신호 변경]</i>\n"}, {"id": 14, "type": "conversation", "attrs": ["[ROBO_Head]"], "content": "<i>행동 프로그램 입력.....\n조작/행동이 거부되었습니다.\n부여된 최우선 지령과의 충돌 가능성</i>\n"}, {"id": 15, "type": "conversation", "attrs": ["[ROBO_Head]"], "content": "<i>......</i>\n"}, {"id": 16, "type": "conversation", "attrs": ["[ROBO_Head]"], "content": "<i>행동 프로그램 입력.....\n조작/행동이 거부되었습니다.\n부여된 최우선 지령과의 충돌 가능성</i>\n"}, {"id": 17, "type": "conversation", "attrs": ["[ROBO_Head]"], "content": "<i>......</i>\n"}, {"id": 18, "type": "conversation", "attrs": ["[ROBO_Head]"], "content": "<i>불러오기 Local.log……100%\n이전 종료 기록: 698/06/02 23:16:50'23\"\n종료중 기록된 녹화 데이터: Cam_Robo_698_06_02</i>\n"}, {"id": 19, "type": "conversation", "attrs": ["[ROBO_Head]"], "content": "<i>......</i>\n"}, {"id": 20, "type": "conversation", "attrs": ["[ROBO_Head]"], "content": "<i>영상 재생：Cam_Robo_698_06_02</i>\n"}, {"id": 21, "type": "conversation", "attrs": ["[ROBO_Head]"], "content": "<i>......</i>\n"}, {"id": 22, "type": "conversation", "attrs": ["[ROBO_Head]"], "content": "<i>재생 실패.\n메모리 유닛 리셋 오류. 다른 파일을 선택하여 주십시오.</i>\n"}, {"id": 23, "type": "conversation", "attrs": ["[ROBO_Head]"], "content": "<i>......</i>\n"}, {"id": 24, "type": "conversation", "attrs": ["[ROBO_Head]"], "content": "<i>영상 재생：Cam_Robo_697_04_06_1</i>\n"}, {"id": 25, "type": "conversation", "attrs": ["[ROBO_Head]"], "content": "<i>재생 시작</i>\n"}, {"id": 26, "type": "text", "attrs": [], "content": "<i>[신호 중단]</i>\n"}], [{"id": 0, "type": "bgm", "attrs": ["Station"], "content": ""}, {"id": 1, "type": "conversation", "attrs": ["清潔工 A"], "content": "先生……先生……？\n"}, {"id": 2, "type": "sound", "attrs": ["ROBO_On", "ROBO_Head 啟動"], "content": ""}, {"id": 3, "type": "conversation", "attrs": ["[ROBO_Head]"], "content": "<i>本機，已正常啟動，執行自我診斷……未完成。\n偵測到硬體多處發生物理損傷。</i>\n"}, {"id": 4, "type": "conversation", "attrs": ["清潔工 B"], "content": "搞什麼啊？代理機器人嗎？\n這班列車已經停止服務囉，請快點下車，我們要打掃了。\n"}, {"id": 5, "type": "conversation", "attrs": ["[ROBO_Head]"], "content": "<i>……。\n提問：此處……座標位置？</i>\n"}, {"id": 6, "type": "conversation", "attrs": ["清潔工 A"], "content": "啊？Node 08 啊。你在哪裡連線操作的啊？請趕快把機器人開走。\n"}, {"id": 7, "type": "conversation", "attrs": ["[ROBO_Head]"], "content": "<i>……。\nNora 呢？</i>\n"}, {"id": 8, "type": "conversation", "attrs": ["清潔工 B"], "content": "吭？什麼啊？是秀逗了嗎？\n怎麼辦？要通知站務所嗎？\n"}, {"id": 9, "type": "conversation", "attrs": ["清潔工 A"], "content": "嗯。這裡是 B 月台，發現一台破損的代理機器人，好像已經跟主人斷線了，它在這邊造成我們困擾，請派人來處理……\n"}, {"id": 10, "type": "conversation", "attrs": ["[ROBO_Head]"], "content": "<i>失禮了。</i>\n"}, {"id": 11, "type": "sound", "attrs": ["ROBO_Step", "腳步"], "content": ""}, {"id": 12, "type": "conversation", "attrs": ["清潔工 B"], "content": "欸，喂！\n"}, {"id": 13, "type": "text", "attrs": [], "content": "<i>[→切換訊號]</i>\n"}, {"id": 14, "type": "conversation", "attrs": ["[ROBO_Head]"], "content": "<i>輸入行動規劃……\n操作/行為遭拒，與最高指令衝突。</i>\n"}, {"id": 15, "type": "conversation", "attrs": ["[ROBO_Head]"], "content": "<i>……。</i>\n"}, {"id": 16, "type": "conversation", "attrs": ["[ROBO_Head]"], "content": "<i>輸入行動規劃……\n操作/行為遭拒，與最高指令衝突。</i>\n"}, {"id": 17, "type": "conversation", "attrs": ["[ROBO_Head]"], "content": "<i>……。</i>\n"}, {"id": 18, "type": "conversation", "attrs": ["[ROBO_Head]"], "content": "<i>讀取 Local.log……100%\n上一次關機紀錄：698/06/02 23:16:50'23\"\n關機中有一則錄影訊息：Cam_Robo_698_06_02</i>\n"}, {"id": 19, "type": "conversation", "attrs": ["[ROBO_Head]"], "content": "<i>……。</i>\n"}, {"id": 20, "type": "conversation", "attrs": ["[ROBO_Head]"], "content": "<i>播放錄影：Cam_Robo_698_06_02</i>\n"}, {"id": 21, "type": "conversation", "attrs": ["[ROBO_Head]"], "content": "<i>……。</i>\n"}, {"id": 22, "type": "conversation", "attrs": ["[ROBO_Head]"], "content": "<i>播放失敗。\n記憶單元重置錯誤，請選擇其他檔案以供偵錯。</i>\n"}, {"id": 23, "type": "conversation", "attrs": ["[ROBO_Head]"], "content": "<i>……。</i>\n"}, {"id": 24, "type": "conversation", "attrs": ["[ROBO_Head]"], "content": "<i>播放錄影：Cam_Robo_697_04_06_1</i>\n"}, {"id": 25, "type": "conversation", "attrs": ["[ROBO_Head]"], "content": "<i>開始播放。</i>\n"}, {"id": 26, "type": "text", "attrs": [], "content": "<i>[訊號中斷]</i>\n"}], [{"id": 0, "type": "bgm", "attrs": ["Station"], "content": ""}, {"id": 1, "type": "conversation", "attrs": ["清洁工 A"], "content": "先生……先生……？\n"}, {"id": 2, "type": "sound", "attrs": ["ROBO_On", "ROBO_Head 启动"], "content": ""}, {"id": 3, "type": "conversation", "attrs": ["[ROBO_Head]"], "content": "<i>本机，已正常启动，执行自我诊断……未完成。\n侦测到硬体多处发生物理损伤。 </i>\n"}, {"id": 4, "type": "conversation", "attrs": ["清洁工 B"], "content": "搞什么啊？代理机器人吗？\n这班列车已经停止服务啰，请快点下车，我们要打扫了。\n"}, {"id": 5, "type": "conversation", "attrs": ["[ROBO_Head]"], "content": "<i>……。\n提问：此处……座标位置？ </i>\n"}, {"id": 6, "type": "conversation", "attrs": ["清洁工 A"], "content": "啊？ Node 08 啊。你在哪里连线操作的啊？请赶快把机器人开走。\n"}, {"id": 7, "type": "conversation", "attrs": ["[ROBO_Head]"], "content": "<i>……。\nNora 呢？ </i>\n"}, {"id": 8, "type": "conversation", "attrs": ["清洁工 B"], "content": "吭？什么啊？是秀逗了吗？\n怎么办？要通知站务所吗？\n"}, {"id": 9, "type": "conversation", "attrs": ["清洁工 A"], "content": "嗯。这里是 B 月台，发现一台破损的代理机器人，好像已经跟主人断线了，它在这边造成我们困扰，请派人来处理……\n"}, {"id": 10, "type": "conversation", "attrs": ["[ROBO_Head]"], "content": "<i>失礼了。 </i>\n"}, {"id": 11, "type": "sound", "attrs": ["ROBO_Step", "脚步"], "content": ""}, {"id": 12, "type": "conversation", "attrs": ["清洁工 B"], "content": "欸，喂！\n"}, {"id": 13, "type": "text", "attrs": [], "content": "<i>[→切换讯号]</i>\n"}, {"id": 14, "type": "conversation", "attrs": ["[ROBO_Head]"], "content": "<i>输入行动规划……\n操作/行为遭拒，与最高指令冲突。 </i>\n"}, {"id": 15, "type": "conversation", "attrs": ["[ROBO_Head]"], "content": "<i>……。 </i>\n"}, {"id": 16, "type": "conversation", "attrs": ["[ROBO_Head]"], "content": "<i>输入行动规划……\n操作/行为遭拒，与最高指令冲突。 </i>\n"}, {"id": 17, "type": "conversation", "attrs": ["[ROBO_Head]"], "content": "<i>……。 </i>\n"}, {"id": 18, "type": "conversation", "attrs": ["[ROBO_Head]"], "content": "<i>读取 Local.log……100%\n上一次关机纪录：698/06/02 23:16:50'23\"\n关机中有一则录影讯息：Cam_Robo_698_06_02</i>\n"}, {"id": 19, "type": "conversation", "attrs": ["[ROBO_Head]"], "content": "<i>……。 </i>\n"}, {"id": 20, "type": "conversation", "attrs": ["[ROBO_Head]"], "content": "<i>播放录影：Cam_Robo_698_06_02</i>\n"}, {"id": 21, "type": "conversation", "attrs": ["[ROBO_Head]"], "content": "<i>……。 </i>\n"}, {"id": 22, "type": "conversation", "attrs": ["[ROBO_Head]"], "content": "<i>播放失败。\n记忆单元重置错误，请选择其他档案以供侦错。 </i>\n"}, {"id": 23, "type": "conversation", "attrs": ["[ROBO_Head]"], "content": "<i>……。 </i>\n"}, {"id": 24, "type": "conversation", "attrs": ["[ROBO_Head]"], "content": "<i>播放录影：Cam_Robo_697_04_06_1</i>\n"}, {"id": 25, "type": "conversation", "attrs": ["[ROBO_Head]"], "content": "<i>开始播放。 </i>\n"}, {"id": 26, "type": "text", "attrs": [], "content": "<i>[讯号中断]</i>\n"}]]}