{"id": "xos038", "name": "Cam_Port33_702_11_17", "res": null, "contents": [[{"id": 0, "type": "conversation", "attrs": ["Cherry"], "content": "The transporter is almost here. Didn't think we would actually survive these seven days without a hitch.\n... R, thanks a lot.\n"}, {"id": 1, "type": "conversation", "attrs": ["ConneR"], "content": "I've only done this by myself before. Hunting for food for three people turned out to be a bit tougher than I thought. However, it made for a good experience.\n"}, {"id": 2, "type": "conversation", "attrs": ["Xenon"], "content": "... Thanks for the help. We ought to be on our way.\n"}, {"id": 3, "type": "conversation", "attrs": ["ConneR"], "content": "Don't let down your guard too soon. Did you young fellas not notice? Starting from two days ago... we've got company.\n"}, {"id": 4, "type": "conversation", "attrs": ["Xenon"], "content": "......?\n"}, {"id": 5, "type": "conversation", "attrs": ["ConneR"], "content": "Some other \"rats\" are also here...\n"}, {"id": 6, "type": "sound", "attrs": ["MetalImpact", "Things Crashing"], "content": ""}, {"id": 7, "type": "conversation", "attrs": ["Member A"], "content": "<font size=\"1.6\">HEY! Be careful!</font>\n"}, {"id": 8, "type": "conversation", "attrs": ["Cherry"], "content": "......!?\n"}, {"id": 9, "type": "conversation", "attrs": ["ConneR"], "content": "Speak of the devil…\n"}, {"id": 10, "type": "conversation", "attrs": ["Xenon"], "content": "... Are they... \"gravediggers\"? What do we do? They seem like serious trouble. They all got guns too.\n"}, {"id": 11, "type": "conversation", "attrs": ["Cherry"], "content": "Let's go. It's none of our business.\n"}, {"id": 12, "type": "conversation", "attrs": ["Xenon"], "content": "What's in those crates...\n"}, {"id": 13, "type": "conversation", "attrs": ["Cherry"], "content": "Simon, the transporter is almost here. It's best that we don't get into a fight with them. Just pretend that we didn't see anything... Right? R?\n...... R?\n"}, {"id": 14, "type": "text", "attrs": [], "content": "<i>[→Signal Switches]</i>\n"}, {"id": 15, "type": "conversation", "attrs": ["Member A"], "content": "Be careful! This cargo is easily worth ten times more than your life ever will.\n"}, {"id": 16, "type": "conversation", "attrs": ["Member B"], "content": "I know, I know.\n"}, {"id": 17, "type": "conversation", "attrs": ["ConneR"], "content": "Greetings~ Gentlemen. Enjoying the night?\n"}, {"id": 18, "type": "conversation", "attrs": ["Member C"], "content": "... Who's there!?\n"}, {"id": 19, "type": "sound", "attrs": ["Trigger", "Loads Gun"], "content": ""}, {"id": 20, "type": "conversation", "attrs": ["ConneR"], "content": "Hoho~! How scary. No need to be so nervous. I'm one of your peers. Just want to make some friends; nothing wrong with that, right? I'm quite interested in what you folks have in those crates. Are you down for a trade?\n"}, {"id": 21, "type": "conversation", "attrs": ["Member A"], "content": "Trade my a**! DIE!!\n"}, {"id": 22, "type": "sound", "attrs": ["GunShot_03", "Gunshot"], "content": ""}, {"id": 23, "type": "conversation", "attrs": ["ConneR"], "content": "... My oh my, such hostile people. I originally planned to offer a high price so we could all benefit from this. Well, guess I shouldn't expect rats to understand the beauty of human language...\n"}, {"id": 24, "type": "sound", "attrs": ["GunShot_03", "Gunshot"], "content": ""}, {"id": 25, "type": "conversation", "attrs": ["Member B"], "content": "Shoot him up! Damnit! Why is there somebody else at this place?\n"}, {"id": 26, "type": "conversation", "attrs": ["Member C"], "content": "How would I know!?\n"}, {"id": 27, "type": "sound", "attrs": ["GunShot_03", "Gunshot"], "content": ""}, {"id": 28, "type": "conversation", "attrs": ["ConneR"], "content": "... This numbers disadvantage is certainly a bit annoying.\n"}, {"id": 29, "type": "sound", "attrs": ["Hacking", "Lights off"], "content": ""}, {"id": 30, "type": "conversation", "attrs": ["Member"], "content": "......!?\n"}, {"id": 31, "type": "conversation", "attrs": ["Xenon"], "content": "Now!\n"}, {"id": 32, "type": "sound", "attrs": ["GunShot_03", "Gunshot"], "content": ""}, {"id": 33, "type": "conversation", "attrs": ["Member"], "content": "Argh!\n"}, {"id": 34, "type": "conversation", "attrs": ["ConneR"], "content": "......?\n"}, {"id": 35, "type": "conversation", "attrs": ["Xenon"], "content": "You can come out now. All of them have been dealt with.\n"}, {"id": 36, "type": "conversation", "attrs": ["ConneR"], "content": "(Whistles) So the drone killer can kill people too.\n"}, {"id": 37, "type": "conversation", "attrs": ["Cherry"], "content": "This is a pulse pistol. They merely fainted. Why did you act on your own all of a sudden!?\n"}, {"id": 38, "type": "conversation", "attrs": ["ConneR"], "content": "You fellas could've left after you got the map. I can handle these rats myself just fine. You're the one who turned off the lights, aren't you?\n"}, {"id": 39, "type": "conversation", "attrs": ["Xenon"], "content": "I didn't do it for your sake. It seems that they planned to transport the weapons in these crates to 08. Can't just ignore them.\n"}, {"id": 40, "type": "conversation", "attrs": ["ConneR"], "content": "Oh? Then what do you plan to do?\n"}, {"id": 41, "type": "sound", "attrs": ["GunShot_03", "Gunshot"], "content": ""}, {"id": 42, "type": "conversation", "attrs": ["Cherry"], "content": "Destroy them all.\n"}, {"id": 43, "type": "conversation", "attrs": ["ConneR"], "content": "Awww... what a pity. There was some pretty good stuff in those crates. For example, this baby right here.\n"}, {"id": 44, "type": "conversation", "attrs": ["Xenon"], "content": "......! When did you take that? Put it down. Sherry will destroy it.\n"}, {"id": 45, "type": "conversation", "attrs": ["ConneR"], "content": "Sorry, but my response is no. I'd like to remind you that you still owe me a favor. Consider this gun a payment for everything I did for you.\n"}, {"id": 46, "type": "conversation", "attrs": ["Xenon"], "content": "......\n"}, {"id": 47, "type": "conversation", "attrs": ["ConneR"], "content": "Alright, it's about time I leave too. You two should get to 03 as soon as possible. Once my investigation produces some results, I will contact you two. Before that, feel free to do as you wish... as long as you don't get into trouble.\n"}, {"id": 48, "type": "conversation", "attrs": ["Cherry"], "content": "What trouble...?\n"}, {"id": 49, "type": "conversation", "attrs": ["ConneR"], "content": "<i>*Chuckles*</i> Well, you fellas have \"trouble\" written all over your faces. Farewell, and take care.\n"}, {"id": 50, "type": "sound", "attrs": ["Step_Reverb", "Footsteps"], "content": ""}, {"id": 51, "type": "conversation", "attrs": ["Xenon"], "content": "... He left.\n"}, {"id": 52, "type": "conversation", "attrs": ["Cherry"], "content": "Hey... Simon, check out this news.\n"}, {"id": 53, "type": "conversation", "attrs": ["Xenon"], "content": "... \"A few hours ago, there had been several eyewitness reports from Node 08 that reported abnormal flight patterns from drones. Just now, we've also been gradually receiving news regarding the drones' attacks on the cities.\"... Is this real? What is going on?\n"}, {"id": 54, "type": "conversation", "attrs": ["Cherry"], "content": "JOE! Quick, call him and ask him about this.\n"}, {"id": 55, "type": "conversation", "attrs": ["Xenon"], "content": "On it!\n"}, {"id": 56, "type": "text", "attrs": [], "content": "<i>[Signal Lost]</i>\n"}], [{"id": 0, "type": "conversation", "attrs": ["Cherry"], "content": "もうすぐ来るはず。\nまさか本当に7日も無事に過ごせるとは思わなかった……R、ありがとう。\n"}, {"id": 1, "type": "conversation", "attrs": ["ConneR"], "content": "以前はずっと一人きりだったからな、1度に3人分の食料をしとめるのは、なかなか骨が折れたよ。\nだが、悪くない経験だったと言えるだろう。\n"}, {"id": 2, "type": "conversation", "attrs": ["Xenon"], "content": "……ありがとうございます。\nよし、じゃあ行こう。\n"}, {"id": 3, "type": "conversation", "attrs": ["ConneR"], "content": "安心するのはまだ早い。\n君たちは感じないのか？\n2日前から、ここにいるのは我々だけではない……\n"}, {"id": 4, "type": "conversation", "attrs": ["Xenon"], "content": "……？\n"}, {"id": 5, "type": "conversation", "attrs": ["ConneR"], "content": "「ネズミ」が紛れ込んだようだ……\n"}, {"id": 6, "type": "sound", "attrs": ["MetalImpact", "物がぶつかる"], "content": ""}, {"id": 7, "type": "conversation", "attrs": ["組員 A"], "content": "<font size=\"1.6\">おい！気を付けろ！</font>\n"}, {"id": 8, "type": "conversation", "attrs": ["Cherry"], "content": "……！？\n"}, {"id": 9, "type": "conversation", "attrs": ["ConneR"], "content": "Speaking of the devil……\n"}, {"id": 10, "type": "conversation", "attrs": ["Xenon"], "content": "……「墓荒らし」ですか。\nどうするか……\n奴らは全員銃を所持しているようだし……\n"}, {"id": 11, "type": "conversation", "attrs": ["Cherry"], "content": "行こう。\nあたしらには関係ない。\n"}, {"id": 12, "type": "conversation", "attrs": ["Xenon"], "content": "あの箱の中身は……\n"}, {"id": 13, "type": "conversation", "attrs": ["Cherry"], "content": "Simon、もう列車が来る。\nこんなところで、奴らと面倒を起こしてる暇はない。\nあんたもそう思うでしょ？R……R？\n"}, {"id": 14, "type": "text", "attrs": [], "content": "<i>[→シグナル切り替え]</i>\n"}, {"id": 15, "type": "conversation", "attrs": ["組員 A"], "content": "気をつけろ！\nここにあるものは、お前10人よりずっと値の張る品なんだぞ。\n"}, {"id": 16, "type": "conversation", "attrs": ["組員 B"], "content": "わーってるって。\n"}, {"id": 17, "type": "conversation", "attrs": ["ConneR"], "content": "おやおや、ジェントルマン諸君。\nこんばんは。\n"}, {"id": 18, "type": "conversation", "attrs": ["組員 C"], "content": "……誰だ！\n"}, {"id": 19, "type": "sound", "attrs": ["Trigger", "銃を構える"], "content": ""}, {"id": 20, "type": "conversation", "attrs": ["ConneR"], "content": "おっと、そう怖い顔をしないでくれたまえ。\n私も君たちの同業だ。\nどうだ？友人にならないかね？\n君たちの箱の中身にとても興味がある。\n私と取り引きをしないか？\n"}, {"id": 21, "type": "conversation", "attrs": ["組員 A"], "content": "ふざけんじゃねぇ！死ね！\n"}, {"id": 22, "type": "sound", "attrs": ["GunShot_03", "銃声"], "content": ""}, {"id": 23, "type": "conversation", "attrs": ["ConneR"], "content": "……つれないねぇ。\n高値で買い取ろうと考えていたんだが……\n大人しく取り引きに応じていれば、誰も怪我をせずに済んだものを。\nやはり、ネズミに人の言葉は通じないか……\n"}, {"id": 24, "type": "sound", "attrs": ["GunShot_03", "銃声"], "content": ""}, {"id": 25, "type": "conversation", "attrs": ["組員 B"], "content": "撃ち殺せ！\nくそっ！なんでこんな所に他の人間がいんだよ！\n"}, {"id": 26, "type": "conversation", "attrs": ["組員 C"], "content": "知らねぇよ！\n"}, {"id": 27, "type": "sound", "attrs": ["GunShot_03", "銃声"], "content": ""}, {"id": 28, "type": "conversation", "attrs": ["ConneR"], "content": "……おや、この人数では私がいささか不利なようだ。\n"}, {"id": 29, "type": "sound", "attrs": ["Hacking", "明かりが消える"], "content": ""}, {"id": 30, "type": "conversation", "attrs": ["組員"], "content": "……！？\n"}, {"id": 31, "type": "conversation", "attrs": ["Xenon"], "content": "今だ！\n"}, {"id": 32, "type": "sound", "attrs": ["GunShot_03", "銃声"], "content": ""}, {"id": 33, "type": "conversation", "attrs": ["組員"], "content": "ぐはッ！\n"}, {"id": 34, "type": "conversation", "attrs": ["ConneR"], "content": "……？\n"}, {"id": 35, "type": "conversation", "attrs": ["Xenon"], "content": "もう出てきていいですよ。\n片付きました。\n"}, {"id": 36, "type": "conversation", "attrs": ["ConneR"], "content": "ひゅ～っ\nなんと、ドローンキラーは人も殺せたのか。\n"}, {"id": 37, "type": "conversation", "attrs": ["Cherry"], "content": "これは、パルスガン。\nこいつらは気絶しただけ。\nてか！勝手な行動すんな！\n"}, {"id": 38, "type": "conversation", "attrs": ["ConneR"], "content": "君たちはもう地図を手に入れたはずだ。\n私を置いて行くこともできただろう？\n私は一人でもネズミ退治くらいはできたさ。\n明かりを消したのは君かね？\n"}, {"id": 39, "type": "conversation", "attrs": ["Xenon"], "content": "あなたのためじゃありません。\n奴らはこの箱の中の武器をNode08に運ぼうとしていました。\nそれを見過ごすことはできなかっただけです。\n"}, {"id": 40, "type": "conversation", "attrs": ["ConneR"], "content": "ほぉ？\nでは、君はこれらをどうするつもりかね？\n"}, {"id": 41, "type": "sound", "attrs": ["GunShot_03", "銃声"], "content": ""}, {"id": 42, "type": "conversation", "attrs": ["Cherry"], "content": "全部潰す。\n"}, {"id": 43, "type": "conversation", "attrs": ["ConneR"], "content": "あああ……残念だ。\n中には良い品もあるというのに。\n例えば、これとかな。\n"}, {"id": 44, "type": "conversation", "attrs": ["Xenon"], "content": "……！いつのまに……！？\nそれを放してください。\nSherryが壊します。\n"}, {"id": 45, "type": "conversation", "attrs": ["ConneR"], "content": "それはできない相談だ。\n君たちは私に借りがあるはずだろう？\nこれで貸し借りなしだ。\n"}, {"id": 46, "type": "conversation", "attrs": ["Xenon"], "content": "………\n"}, {"id": 47, "type": "conversation", "attrs": ["ConneR"], "content": "もういいだろう。\n私はここらで失礼するよ。\n君たちは早く03に向かうといい。\nある程度目途が経ったら、また君たちに連絡する。\nそれまでは、好きにしていてくれたまえ。\n派手なことをしなければ、何をしても構わない。\n"}, {"id": 48, "type": "conversation", "attrs": ["Cherry"], "content": "派手な事……？\n"}, {"id": 49, "type": "conversation", "attrs": ["ConneR"], "content": "君たちの組み合わせは、明らかに派手な事をやらかしそうな組み合わせだ。\nははは、では、また会おう。\n"}, {"id": 50, "type": "sound", "attrs": ["Step_Reverb", "足音"], "content": ""}, {"id": 51, "type": "conversation", "attrs": ["Xenon"], "content": "……行ったか。\n"}, {"id": 52, "type": "conversation", "attrs": ["Cherry"], "content": "ねぇ……Simon、これ見て。\nこのニュース。\n"}, {"id": 53, "type": "conversation", "attrs": ["Xenon"], "content": "……「数時間前、Node 08にてドローンが集団飛行している様子が目撃された後、ドローンが無差別攻撃を行っているという情報が多数寄せられました。」\n……は？\n何があったんだ？\n"}, {"id": 54, "type": "conversation", "attrs": ["Cherry"], "content": "JOE！JOEに電話しよう！\n"}, {"id": 55, "type": "conversation", "attrs": ["Xenon"], "content": "あぁ！\n"}, {"id": 56, "type": "text", "attrs": [], "content": "<i>[電波切断]</i>\n"}], [{"id": 0, "type": "conversation", "attrs": ["Cherry"], "content": "車快來了。想不到我們真的平安熬過這七天……R，謝謝你。\n"}, {"id": 1, "type": "conversation", "attrs": ["ConneR"], "content": "以前一直是一個人的，要一次獵到三人份食物果然還是有點辛苦。對我是很不錯的經驗呢。\n"}, {"id": 2, "type": "conversation", "attrs": ["Xenon"], "content": "……謝了，那我們出發吧。\n"}, {"id": 3, "type": "conversation", "attrs": ["ConneR"], "content": "別鬆懈得太早，你們都沒注意到嗎？從兩天前開始……這裡不只我們。\n"}, {"id": 4, "type": "conversation", "attrs": ["Xenon"], "content": "……？\n"}, {"id": 5, "type": "conversation", "attrs": ["ConneR"], "content": "還有其他「鼠輩」……\n"}, {"id": 6, "type": "sound", "attrs": ["MetalImpact", "物品碰撞"], "content": ""}, {"id": 7, "type": "conversation", "attrs": ["組員 A"], "content": "<font size=\"1.6\">喂！小心點！</font>\n"}, {"id": 8, "type": "conversation", "attrs": ["Cherry"], "content": "……！？\n"}, {"id": 9, "type": "conversation", "attrs": ["ConneR"], "content": "Speaking of the devil……\n"}, {"id": 10, "type": "conversation", "attrs": ["Xenon"], "content": "……是「盜墓者」？怎麼辦？他們看起來不好惹，手上都有槍。\n"}, {"id": 11, "type": "conversation", "attrs": ["Cherry"], "content": "走吧，不關我們的事。\n"}, {"id": 12, "type": "conversation", "attrs": ["Xenon"], "content": "那些箱子裡裝的……\n"}, {"id": 13, "type": "conversation", "attrs": ["Cherry"], "content": "Simon，車快來了。還是別跟他們起衝突，假裝沒看到比較好……對吧？R？\n……R？\n"}, {"id": 14, "type": "text", "attrs": [], "content": "<i>[→切換訊號]</i>\n"}, {"id": 15, "type": "conversation", "attrs": ["組員 A"], "content": "小心點！這些貨可是你十個人頭都賠不起。\n"}, {"id": 16, "type": "conversation", "attrs": ["組員 B"], "content": "知道啦。\n"}, {"id": 17, "type": "conversation", "attrs": ["ConneR"], "content": "呀～Gentlemen，晚安啊。\n"}, {"id": 18, "type": "conversation", "attrs": ["組員 C"], "content": "……誰！？\n"}, {"id": 19, "type": "sound", "attrs": ["Trigger", "舉槍"], "content": ""}, {"id": 20, "type": "conversation", "attrs": ["ConneR"], "content": "喔喔！真可怕吶。別緊張，我也是同行，我們交個朋友吧？我對你們箱子裡的東西頗感興趣，方便做個交易嗎？\n"}, {"id": 21, "type": "conversation", "attrs": ["組員 A"], "content": "交你老○！去死！\n"}, {"id": 22, "type": "sound", "attrs": ["GunShot_03", "槍聲"], "content": ""}, {"id": 23, "type": "conversation", "attrs": ["ConneR"], "content": "……很不友善啊。本來想出個高價的，誰都不用受傷。果然是群聽不懂人話的鼠輩……\n"}, {"id": 24, "type": "sound", "attrs": ["GunShot_03", "槍聲"], "content": ""}, {"id": 25, "type": "conversation", "attrs": ["組員 B"], "content": "把他打爛！可惡，為什麼這種地方會有其他人？\n"}, {"id": 26, "type": "conversation", "attrs": ["組員 C"], "content": "我哪知道！？\n"}, {"id": 27, "type": "sound", "attrs": ["GunShot_03", "槍聲"], "content": ""}, {"id": 28, "type": "conversation", "attrs": ["ConneR"], "content": "……這人數對我有點不利呢。\n"}, {"id": 29, "type": "sound", "attrs": ["Hacking", "熄燈"], "content": ""}, {"id": 30, "type": "conversation", "attrs": ["組員"], "content": "……！？\n"}, {"id": 31, "type": "conversation", "attrs": ["Xenon"], "content": "現在！\n"}, {"id": 32, "type": "sound", "attrs": ["GunShot_03", "槍聲"], "content": ""}, {"id": 33, "type": "conversation", "attrs": ["組員"], "content": "呃啊！\n"}, {"id": 34, "type": "conversation", "attrs": ["ConneR"], "content": "……？\n"}, {"id": 35, "type": "conversation", "attrs": ["Xenon"], "content": "出來吧，都解決了。\n"}, {"id": 36, "type": "conversation", "attrs": ["ConneR"], "content": "（口哨）想不到無人機殺手也會殺人啊。\n"}, {"id": 37, "type": "conversation", "attrs": ["Cherry"], "content": "這是脈衝槍，他們只是暈過去而已。你幹嘛擅自行動啊！？\n"}, {"id": 38, "type": "conversation", "attrs": ["ConneR"], "content": "明明拿到地圖你們就可以走了，我自己一個人也能搞定這些鼠輩的。是你把燈弄熄的對吧？\n"}, {"id": 39, "type": "conversation", "attrs": ["Xenon"], "content": "我不是為了你。這些箱子裡的武器，他們打算運到 08 的樣子，不能坐視不管。\n"}, {"id": 40, "type": "conversation", "attrs": ["ConneR"], "content": "喔？那你打算怎麼辦？\n"}, {"id": 41, "type": "sound", "attrs": ["GunShot_03", "槍聲"], "content": ""}, {"id": 42, "type": "conversation", "attrs": ["Cherry"], "content": "全部毀掉。\n"}, {"id": 43, "type": "conversation", "attrs": ["ConneR"], "content": "啊啊……真可惜，當中有些好貨呢，比如這把。\n"}, {"id": 44, "type": "conversation", "attrs": ["Xenon"], "content": "……！你什麼時候偷拿的？放下吧，Sherry 會銷毀它。\n"}, {"id": 45, "type": "conversation", "attrs": ["ConneR"], "content": "不要。你還欠我個人情呢，這把槍就當我們扯平了。\n"}, {"id": 46, "type": "conversation", "attrs": ["Xenon"], "content": "……。\n"}, {"id": 47, "type": "conversation", "attrs": ["ConneR"], "content": "好了，我也差不多該走了。你們也快去 03 吧，等我這調查有個結果我自然會聯絡你們，在那之前就請你們自便吧，別搞什麼大事就好。\n"}, {"id": 48, "type": "conversation", "attrs": ["Cherry"], "content": "搞什麼大事……？\n"}, {"id": 49, "type": "conversation", "attrs": ["ConneR"], "content": "你們這對組合一臉就是會搞大事的樣子呢，呵呵。那麼，再見了。\n"}, {"id": 50, "type": "sound", "attrs": ["Step_Reverb", "腳步"], "content": ""}, {"id": 51, "type": "conversation", "attrs": ["Xenon"], "content": "……走掉了。\n"}, {"id": 52, "type": "conversation", "attrs": ["Cherry"], "content": "喂……Simon，你看這則新聞。\n"}, {"id": 53, "type": "conversation", "attrs": ["Xenon"], "content": "……「幾小時前 Node 08 傳出數架無人機異常飛行的目擊事件之後，方才本台也陸續接獲了無人機開始對城市進行攻擊的消息」……真的假的？怎麼回事？\n"}, {"id": 54, "type": "conversation", "attrs": ["Cherry"], "content": "JOE！快點打給他問問看。\n"}, {"id": 55, "type": "conversation", "attrs": ["Xenon"], "content": "嗯！\n"}, {"id": 56, "type": "text", "attrs": [], "content": "<i>[訊號中斷]</i>\n"}], [{"id": 0, "type": "conversation", "attrs": ["Cherry"], "content": "차가 곧 도착할 거야.\n7일 동안이나 이렇게 아무 일 없이 편안하게 보낼 수 있을 줄은 생각도 못 했어... \n고맙다, R...\n"}, {"id": 1, "type": "conversation", "attrs": ["ConneR"], "content": "예전엔 제 몸 하나만 잘 챙기면 별문제 없었는데, 이번엔 한 번에 3명 분의 식량을 조달해야 하니 조금 애 좀 먹었던 것 같군요. 뭐, 그래도 꽤 나쁘지 않은 경험이었습니다.\n"}, {"id": 2, "type": "conversation", "attrs": ["Xenon"], "content": "...신세 졌군.\n그럼 출발하자.\n"}, {"id": 3, "type": "conversation", "attrs": ["ConneR"], "content": "벌써부터 이렇게 긴장이 풀어져서야...\n아직 눈치채지 못하셨나요?\n이틀 전부터... 이곳에 있던 사람은 저희뿐만이 아니었습니다만...\n"}, {"id": 4, "type": "conversation", "attrs": ["Xenon"], "content": "......?\n"}, {"id": 5, "type": "conversation", "attrs": ["ConneR"], "content": "「쥐새끼」가 돌아다니고 있었다는 얘깁니다...\n"}, {"id": 6, "type": "sound", "attrs": ["MetalImpact", "물건들이 부딪힌다"], "content": ""}, {"id": 7, "type": "conversation", "attrs": ["조직원 A"], "content": "<font size=\"1.6\">어이! 조심하라고!</font>\n"}, {"id": 8, "type": "conversation", "attrs": ["Cherry"], "content": "......!?\n"}, {"id": 9, "type": "conversation", "attrs": ["ConneR"], "content": "Speaking of the devil......\n"}, {"id": 10, "type": "conversation", "attrs": ["Xenon"], "content": "......「도굴꾼」인가!? 어떡하지? 모두 총을 지니고 있어 상대하기 까다롭겠어.\n"}, {"id": 11, "type": "conversation", "attrs": ["Cherry"], "content": "가자. 우리가 상관할 바 아니니까.\n"}, {"id": 12, "type": "conversation", "attrs": ["Xenon"], "content": "저 상자에 들어있는 것들은...\n"}, {"id": 13, "type": "conversation", "attrs": ["Cherry"], "content": "Simon, 차가 곧 올 거야. 저들과 불필요한 충돌을 일으킬 때가 아니야. 이번만큼은 그냥 못 본 셈 치고 넘어가자. R도 동의하지?\n......R?\n"}, {"id": 14, "type": "text", "attrs": [], "content": "<i>[→신호 변경]</i>\n"}, {"id": 15, "type": "conversation", "attrs": ["조직원 A"], "content": "조심하라니까!\n네 몸뚱어리 10개보다도 훨씬 비싼 물건이라고!\n"}, {"id": 16, "type": "conversation", "attrs": ["조직원 B"], "content": "알았다니까.\n"}, {"id": 17, "type": "conversation", "attrs": ["ConneR"], "content": "안녕하십니까, Gentlemen.\n좋은 밤이군요.\n"}, {"id": 18, "type": "conversation", "attrs": ["조직원 C"], "content": "......누구냐!?\n"}, {"id": 19, "type": "sound", "attrs": ["Trigger", "총을 꺼낸다"], "content": ""}, {"id": 20, "type": "conversation", "attrs": ["ConneR"], "content": "워이~ 워이! 그렇게 무섭게 나오실 필요 없습니다. 긴장하지 마시지요. 저도 같은 업종 사람이니까.\n전 여러분들이 가진 그 상자 속 물건들에 아주 관심이 많답니다. 어떻습니까? 저와 거래하시지 않겠습니까?\n"}, {"id": 21, "type": "conversation", "attrs": ["조직원 A"], "content": "거래는 X발 무슨! 뒈X버려!\n"}, {"id": 22, "type": "sound", "attrs": ["GunShot_03", "총성"], "content": ""}, {"id": 23, "type": "conversation", "attrs": ["ConneR"], "content": "......정말 이렇게 불친절해서야... 전 진심으로 여러분께 상상도 못할 큰 액수를 제시하려 했습니다만... 다치는 사람 없이 평화롭게 거래를 한다는 것이 이렇게나 어려운 일이라니... 역시나 쥐새끼라 그런지 사람 말을 잘 못 알아듣는 것 같군요...\n"}, {"id": 24, "type": "sound", "attrs": ["GunShot_03", "총성"], "content": ""}, {"id": 25, "type": "conversation", "attrs": ["조직원 B"], "content": "당장 없애버려! 제길, 어째서 이런 곳에 사람이 있는 거야?\n"}, {"id": 26, "type": "conversation", "attrs": ["조직원 C"], "content": "내가 어떻게 알아!?\n"}, {"id": 27, "type": "sound", "attrs": ["GunShot_03", "총성"], "content": ""}, {"id": 28, "type": "conversation", "attrs": ["ConneR"], "content": "...이 정도 인원은 저에게도 조금 벅찬 것 같군요.\n"}, {"id": 29, "type": "sound", "attrs": ["Hacking", "불이 꺼진다"], "content": ""}, {"id": 30, "type": "conversation", "attrs": ["조직원"], "content": "......!?\n"}, {"id": 31, "type": "conversation", "attrs": ["Xenon"], "content": "지금이다!\n"}, {"id": 32, "type": "sound", "attrs": ["GunShot_03", "총성"], "content": ""}, {"id": 33, "type": "conversation", "attrs": ["조직원"], "content": "우아아아악!\n"}, {"id": 34, "type": "conversation", "attrs": ["ConneR"], "content": "........?\n"}, {"id": 35, "type": "conversation", "attrs": ["Xenon"], "content": "나와도 돼. 전부 해결됐어.\n"}, {"id": 36, "type": "conversation", "attrs": ["ConneR"], "content": "(휘파람) 드론만 잘 파괴하는 줄 알았는데 사람도 잘 처리하시는군요.\n"}, {"id": 37, "type": "conversation", "attrs": ["Cherry"], "content": "이건 펄스건이라고. 저 녀석들은 잠깐 기절했을 뿐이고. 어째서 이런 짓을 벌인 거야!?\n"}, {"id": 38, "type": "conversation", "attrs": ["ConneR"], "content": "지도를 얻었으면 그만 떠나셔도 됐을 텐데. 이런 쥐새끼들을 처리하는 일은 저 혼자서도 충분합니다. 굳이 불까지 꺼주시고 말이죠?\n"}, {"id": 39, "type": "conversation", "attrs": ["Xenon"], "content": "당신을 위해서 한 일이 아니야. 이 상자 안에 있는 무기들은 08로 보내질 예정이었어. 가만히 앉아서 못 본 체할 순 없지.\n"}, {"id": 40, "type": "conversation", "attrs": ["ConneR"], "content": "응? 그럼 다른 계획이라도?\n"}, {"id": 41, "type": "sound", "attrs": ["GunShot_03", "총성"], "content": ""}, {"id": 42, "type": "conversation", "attrs": ["Cherry"], "content": "전부 못 쓰게 만들어버려야지.\n"}, {"id": 43, "type": "conversation", "attrs": ["ConneR"], "content": "하하하... 정말 아쉽군요. 이 중에 몇 자루는 지금 이 총보다 훨씬 좋은 제품인데 말이죠.\n"}, {"id": 44, "type": "conversation", "attrs": ["Xenon"], "content": "...!? 대체 언제 몰래 챙겨둔 거지? 당장 내려놔.\n"}, {"id": 45, "type": "conversation", "attrs": ["ConneR"], "content": "그럴 순 없죠. 예전에 저한테 진 빚이 있지 않습니까? 이 총 한 자루로 비긴셈 쳤으면 하는군요.\n"}, {"id": 46, "type": "conversation", "attrs": ["Xenon"], "content": "......\n"}, {"id": 47, "type": "conversation", "attrs": ["ConneR"], "content": "저도 이제 그만 가봐야 할 것 같습니다. 여러분도 어서 03으로 향하셔야겠습니다. 제가 이곳에서 뭔가 발견하게 되면 자연스럽게 여러분께 연락이 갈 겁니다. 그때까지 각자 알아서 잘 처신하시도록. 큰 문제만 일으키지 않는다면 별 탈 없을 겁니다.\n"}, {"id": 48, "type": "conversation", "attrs": ["Cherry"], "content": "또 무슨 일을 꾸미는 거지...?\n"}, {"id": 49, "type": "conversation", "attrs": ["ConneR"], "content": "그런데 여러분이 함께 있는 모습을 보니, 뭔가 큰 문제를 일으킬 것 같은 기분이 가시질 않는군요. 하하하! \n그럼, 전 이만.\n"}, {"id": 50, "type": "sound", "attrs": ["Step_Reverb", "발걸음"], "content": ""}, {"id": 51, "type": "conversation", "attrs": ["Xenon"], "content": "......가버렸어.\n"}, {"id": 52, "type": "conversation", "attrs": ["Cherry"], "content": "저기... Simon, 이 뉴스 좀 봐야 할 것 같은데.\n"}, {"id": 53, "type": "conversation", "attrs": ["Xenon"], "content": "......「몇 시간 전, Node 08에서 다수의 드론이 비행 오작동을 일으키고 있다는 목격자가 나온 이후로, 드론이 도시에 공격을 가하기 시작했다는 제보가 계속해서 들어오고 있는 상황입니다.」... 말도 안 돼! 어떻게 이런 일이!\n"}, {"id": 54, "type": "conversation", "attrs": ["Cherry"], "content": "JOE! 빨리 걔한테 전화해봐!\n"}, {"id": 55, "type": "conversation", "attrs": ["Xenon"], "content": "알았어!\n"}, {"id": 56, "type": "text", "attrs": [], "content": "<i>[신호 중단]</i>\n"}], [{"id": 0, "type": "conversation", "attrs": ["Cherry"], "content": "車快來了。想不到我們真的平安熬過這七天……R，謝謝你。\n"}, {"id": 1, "type": "conversation", "attrs": ["ConneR"], "content": "以前一直是一個人的，要一次獵到三人份食物果然還是有點辛苦。對我是很不錯的經驗呢。\n"}, {"id": 2, "type": "conversation", "attrs": ["Xenon"], "content": "……謝了，那我們出發吧。\n"}, {"id": 3, "type": "conversation", "attrs": ["ConneR"], "content": "別鬆懈得太早，你們都沒注意到嗎？從兩天前開始……這裡不只我們。\n"}, {"id": 4, "type": "conversation", "attrs": ["Xenon"], "content": "……？\n"}, {"id": 5, "type": "conversation", "attrs": ["ConneR"], "content": "還有其他「鼠輩」……\n"}, {"id": 6, "type": "sound", "attrs": ["MetalImpact", "物品碰撞"], "content": ""}, {"id": 7, "type": "conversation", "attrs": ["組員 A"], "content": "<font size=\"1.6\">喂！小心點！</font>\n"}, {"id": 8, "type": "conversation", "attrs": ["Cherry"], "content": "……！？\n"}, {"id": 9, "type": "conversation", "attrs": ["ConneR"], "content": "Speaking of the devil……\n"}, {"id": 10, "type": "conversation", "attrs": ["Xenon"], "content": "……是「盜墓者」？怎麼辦？他們看起來不好惹，手上都有槍。\n"}, {"id": 11, "type": "conversation", "attrs": ["Cherry"], "content": "走吧，不關我們的事。\n"}, {"id": 12, "type": "conversation", "attrs": ["Xenon"], "content": "那些箱子裡裝的……\n"}, {"id": 13, "type": "conversation", "attrs": ["Cherry"], "content": "Simon，車快來了。還是別跟他們起衝突，假裝沒看到比較好……對吧？R？\n……R？\n"}, {"id": 14, "type": "text", "attrs": [], "content": "<i>[→切換訊號]</i>\n"}, {"id": 15, "type": "conversation", "attrs": ["組員 A"], "content": "小心點！這些貨可是你十個人頭都賠不起。\n"}, {"id": 16, "type": "conversation", "attrs": ["組員 B"], "content": "知道啦。\n"}, {"id": 17, "type": "conversation", "attrs": ["ConneR"], "content": "呀～Gentlemen，晚安啊。\n"}, {"id": 18, "type": "conversation", "attrs": ["組員 C"], "content": "……誰！？\n"}, {"id": 19, "type": "sound", "attrs": ["Trigger", "舉槍"], "content": ""}, {"id": 20, "type": "conversation", "attrs": ["ConneR"], "content": "喔喔！真可怕吶。別緊張，我也是同行，我們交個朋友吧？我對你們箱子裡的東西頗感興趣，方便做個交易嗎？\n"}, {"id": 21, "type": "conversation", "attrs": ["組員 A"], "content": "交你老○！去死！\n"}, {"id": 22, "type": "sound", "attrs": ["GunShot_03", "槍聲"], "content": ""}, {"id": 23, "type": "conversation", "attrs": ["ConneR"], "content": "……很不友善啊。本來想出個高價的，誰都不用受傷。果然是群聽不懂人話的鼠輩……\n"}, {"id": 24, "type": "sound", "attrs": ["GunShot_03", "槍聲"], "content": ""}, {"id": 25, "type": "conversation", "attrs": ["組員 B"], "content": "把他打爛！可惡，為什麼這種地方會有其他人？\n"}, {"id": 26, "type": "conversation", "attrs": ["組員 C"], "content": "我哪知道！？\n"}, {"id": 27, "type": "sound", "attrs": ["GunShot_03", "槍聲"], "content": ""}, {"id": 28, "type": "conversation", "attrs": ["ConneR"], "content": "……這人數對我有點不利呢。\n"}, {"id": 29, "type": "sound", "attrs": ["Hacking", "熄燈"], "content": ""}, {"id": 30, "type": "conversation", "attrs": ["組員"], "content": "……！？\n"}, {"id": 31, "type": "conversation", "attrs": ["Xenon"], "content": "現在！\n"}, {"id": 32, "type": "sound", "attrs": ["GunShot_03", "槍聲"], "content": ""}, {"id": 33, "type": "conversation", "attrs": ["組員"], "content": "呃啊！\n"}, {"id": 34, "type": "conversation", "attrs": ["ConneR"], "content": "……？\n"}, {"id": 35, "type": "conversation", "attrs": ["Xenon"], "content": "出來吧，都解決了。\n"}, {"id": 36, "type": "conversation", "attrs": ["ConneR"], "content": "（口哨）想不到無人機殺手也會殺人啊。\n"}, {"id": 37, "type": "conversation", "attrs": ["Cherry"], "content": "這是脈衝槍，他們只是暈過去而已。你幹嘛擅自行動啊！？\n"}, {"id": 38, "type": "conversation", "attrs": ["ConneR"], "content": "明明拿到地圖你們就可以走了，我自己一個人也能搞定這些鼠輩的。是你把燈弄熄的對吧？\n"}, {"id": 39, "type": "conversation", "attrs": ["Xenon"], "content": "我不是為了你。這些箱子裡的武器，他們打算運到 08 的樣子，不能坐視不管。\n"}, {"id": 40, "type": "conversation", "attrs": ["ConneR"], "content": "喔？那你打算怎麼辦？\n"}, {"id": 41, "type": "sound", "attrs": ["GunShot_03", "槍聲"], "content": ""}, {"id": 42, "type": "conversation", "attrs": ["Cherry"], "content": "全部毀掉。\n"}, {"id": 43, "type": "conversation", "attrs": ["ConneR"], "content": "啊啊……真可惜，當中有些好貨呢，比如這把。\n"}, {"id": 44, "type": "conversation", "attrs": ["Xenon"], "content": "……！你什麼時候偷拿的？放下吧，Sherry 會銷毀它。\n"}, {"id": 45, "type": "conversation", "attrs": ["ConneR"], "content": "不要。你還欠我個人情呢，這把槍就當我們扯平了。\n"}, {"id": 46, "type": "conversation", "attrs": ["Xenon"], "content": "……。\n"}, {"id": 47, "type": "conversation", "attrs": ["ConneR"], "content": "好了，我也差不多該走了。你們也快去 03 吧，等我這調查有個結果我自然會聯絡你們，在那之前就請你們自便吧，別搞什麼大事就好。\n"}, {"id": 48, "type": "conversation", "attrs": ["Cherry"], "content": "搞什麼大事……？\n"}, {"id": 49, "type": "conversation", "attrs": ["ConneR"], "content": "你們這對組合一臉就是會搞大事的樣子呢，呵呵。那麼，再見了。\n"}, {"id": 50, "type": "sound", "attrs": ["Step_Reverb", "腳步"], "content": ""}, {"id": 51, "type": "conversation", "attrs": ["Xenon"], "content": "……走掉了。\n"}, {"id": 52, "type": "conversation", "attrs": ["Cherry"], "content": "喂……Simon，你看這則新聞。\n"}, {"id": 53, "type": "conversation", "attrs": ["Xenon"], "content": "……「幾小時前 Node 08 傳出數架無人機異常飛行的目擊事件之後，方才本台也陸續接獲了無人機開始對城市進行攻擊的消息」……真的假的？怎麼回事？\n"}, {"id": 54, "type": "conversation", "attrs": ["Cherry"], "content": "JOE！快點打給他問問看。\n"}, {"id": 55, "type": "conversation", "attrs": ["Xenon"], "content": "嗯！\n"}, {"id": 56, "type": "text", "attrs": [], "content": "<i>[訊號中斷]</i>\n"}], [{"id": 0, "type": "conversation", "attrs": ["Cherry"], "content": "车快来了。想不到我们真的平安熬过这七天……R，谢谢你。\n"}, {"id": 1, "type": "conversation", "attrs": ["ConneR"], "content": "以前一直是一个人的，要一次猎到三人份食物果然还是有点辛苦。对我是很不错的经验呢。\n"}, {"id": 2, "type": "conversation", "attrs": ["Xenon"], "content": "……谢了，那我们出发吧。\n"}, {"id": 3, "type": "conversation", "attrs": ["ConneR"], "content": "别松懈得太早，你们都没注意到吗？从两天前开始……这里不只我们。\n"}, {"id": 4, "type": "conversation", "attrs": ["Xenon"], "content": "……？\n"}, {"id": 5, "type": "conversation", "attrs": ["ConneR"], "content": "还有其他「鼠辈」……\n"}, {"id": 6, "type": "sound", "attrs": ["MetalImpact", "物品碰撞"], "content": ""}, {"id": 7, "type": "conversation", "attrs": ["组员 A"], "content": "<font size=\"1.6\">喂！小心点！ </font>\n"}, {"id": 8, "type": "conversation", "attrs": ["Cherry"], "content": "……！ ？\n"}, {"id": 9, "type": "conversation", "attrs": ["ConneR"], "content": "Speaking of the devil……\n"}, {"id": 10, "type": "conversation", "attrs": ["Xenon"], "content": "……是「盗墓者」？怎么办？他们看起来不好惹，手上都有枪。\n"}, {"id": 11, "type": "conversation", "attrs": ["Cherry"], "content": "走吧，不关我们的事。\n"}, {"id": 12, "type": "conversation", "attrs": ["Xenon"], "content": "那些箱子里装的……\n"}, {"id": 13, "type": "conversation", "attrs": ["Cherry"], "content": "Simon，车快来了。还是别跟他们起冲突，假装没看到比较好……对吧？ R？\n……R？\n"}, {"id": 14, "type": "text", "attrs": [], "content": "<i>[→切换讯号]</i>\n"}, {"id": 15, "type": "conversation", "attrs": ["组员 A"], "content": "小心点！这些货可是你十个人头都赔不起。\n"}, {"id": 16, "type": "conversation", "attrs": ["组员 B"], "content": "知道啦。\n"}, {"id": 17, "type": "conversation", "attrs": ["ConneR"], "content": "呀～Gentlemen，晚安啊。\n"}, {"id": 18, "type": "conversation", "attrs": ["组员 C"], "content": "……谁！ ？\n"}, {"id": 19, "type": "sound", "attrs": ["Trigger", "举枪"], "content": ""}, {"id": 20, "type": "conversation", "attrs": ["ConneR"], "content": "喔喔！真可怕呐。别紧张，我也是同行，我们交个朋友吧？我对你们箱子里的东西颇感兴趣，方便做个交易吗？\n"}, {"id": 21, "type": "conversation", "attrs": ["组员 A"], "content": "交你老○！去死！\n"}, {"id": 22, "type": "sound", "attrs": ["GunShot_03", "枪声"], "content": ""}, {"id": 23, "type": "conversation", "attrs": ["ConneR"], "content": "……很不友善啊。本来想出个高价的，谁都不用受伤。果然是群听不懂人话的鼠辈……\n"}, {"id": 24, "type": "sound", "attrs": ["GunShot_03", "枪声"], "content": ""}, {"id": 25, "type": "conversation", "attrs": ["组员 B"], "content": "把他打烂！可恶，为什么这种地方会有其他人？\n"}, {"id": 26, "type": "conversation", "attrs": ["组员 C"], "content": "我哪知道！ ？\n"}, {"id": 27, "type": "sound", "attrs": ["GunShot_03", "枪声"], "content": ""}, {"id": 28, "type": "conversation", "attrs": ["ConneR"], "content": "……这人数对我有点不利呢。\n"}, {"id": 29, "type": "sound", "attrs": ["Hacking", "熄灯"], "content": ""}, {"id": 30, "type": "conversation", "attrs": ["组员"], "content": "……！ ？\n"}, {"id": 31, "type": "conversation", "attrs": ["Xenon"], "content": "现在！\n"}, {"id": 32, "type": "sound", "attrs": ["GunShot_03", "枪声"], "content": ""}, {"id": 33, "type": "conversation", "attrs": ["组员"], "content": "呃啊！\n"}, {"id": 34, "type": "conversation", "attrs": ["ConneR"], "content": "……？\n"}, {"id": 35, "type": "conversation", "attrs": ["Xenon"], "content": "出来吧，都解决了。\n"}, {"id": 36, "type": "conversation", "attrs": ["ConneR"], "content": "（口哨）想不到无人机杀手也会杀人啊。\n"}, {"id": 37, "type": "conversation", "attrs": ["Cherry"], "content": "这是脉冲枪，他们只是晕过去而已。你干嘛擅自行动啊！ ？\n"}, {"id": 38, "type": "conversation", "attrs": ["ConneR"], "content": "明明拿到地图你们就可以走了，我自己一个人也能搞定这些鼠辈的。是你把灯弄熄的对吧？\n"}, {"id": 39, "type": "conversation", "attrs": ["Xenon"], "content": "我不是为了你。这些箱子里的武器，他们打算运到 08 的样子，不能坐视不管。\n"}, {"id": 40, "type": "conversation", "attrs": ["ConneR"], "content": "喔？那你打算怎么办？\n"}, {"id": 41, "type": "sound", "attrs": ["GunShot_03", "枪声"], "content": ""}, {"id": 42, "type": "conversation", "attrs": ["Cherry"], "content": "全部毁掉。\n"}, {"id": 43, "type": "conversation", "attrs": ["ConneR"], "content": "啊啊……真可惜，当中有些好货呢，比如这把。\n"}, {"id": 44, "type": "conversation", "attrs": ["Xenon"], "content": "……！你什么时候偷拿的？放下吧，Sherry 会销毁它。\n"}, {"id": 45, "type": "conversation", "attrs": ["ConneR"], "content": "不要。你还欠我个人情呢，这把枪就当我们扯平了。\n"}, {"id": 46, "type": "conversation", "attrs": ["Xenon"], "content": "……。\n"}, {"id": 47, "type": "conversation", "attrs": ["ConneR"], "content": "好了，我也差不多该走了。你们也快去 03 吧，等我这调查有个结果我自然会联络你们，在那之前就请你们自便吧，别搞什么大事就好。\n"}, {"id": 48, "type": "conversation", "attrs": ["Cherry"], "content": "搞什么大事……？\n"}, {"id": 49, "type": "conversation", "attrs": ["ConneR"], "content": "你们这对组合一脸就是会搞大事的样子呢，呵呵。那么，再见了。\n"}, {"id": 50, "type": "sound", "attrs": ["Step_Reverb", "脚步"], "content": ""}, {"id": 51, "type": "conversation", "attrs": ["Xenon"], "content": "……走掉了。\n"}, {"id": 52, "type": "conversation", "attrs": ["Cherry"], "content": "喂……Simon，你看这则新闻。\n"}, {"id": 53, "type": "conversation", "attrs": ["Xenon"], "content": "……「几小时前 Node 08 传出数架无人机异常飞行的目击事件之后，方才本台也陆续接获了无人机开始对城市进行攻击的消息」……真的假的？怎么回事？\n"}, {"id": 54, "type": "conversation", "attrs": ["Cherry"], "content": "JOE！快点打给他问问看。\n"}, {"id": 55, "type": "conversation", "attrs": ["Xenon"], "content": "嗯！\n"}, {"id": 56, "type": "text", "attrs": [], "content": "<i>[讯号中断]</i>\n"}]]}